pysle/__init__.py
pysle/isletool.py
pysle/phonetics.py
pysle/praattools.py
pysle/pronunciationtools.py
pysle/data/ISLEdict.txt
pysle/utilities/__init__.py
pysle/utilities/constants.py
pysle/utilities/errors.py
pysle/utilities/isle_io.py
pysle/utilities/phonetic_constants.py
pysle/utilities/search.py
pysle/utilities/utils.py
pysle-4.0.2.dist-info/LICENSE
pysle-4.0.2.dist-info/METADATA
pysle-4.0.2.dist-info/WHEEL
pysle-4.0.2.dist-info/top_level.txt
pysle-4.0.2.dist-info/RECORD
