Metadata-Version: 2.1
Name: pysle
Version: 4.0.2
Summary: An interface to ISLEX, an IPA pronunciation dictionary for English with stress and syllable markings.
Home-page: https://github.com/timmahrt/pysle
Author: Tim Mahrt
Author-email: timmahrt@gmail.com
License: LICENSE
Requires-Python: >3.6.0
License-File: LICENSE
Requires-Dist: praatio ~=6.0
Requires-Dist: typing-extensions
